{
  "file_name": "HOUSE_OVERSIGHT_010489.jpg",
  "image_analysis": {
    "type": "document",
    "description": "A scanned page from a document, featuring a collage of four photographs with corresponding captions. The photographs depict Jeffrey Epstein with various individuals, a booking photo, and an aerial view of a correctional facility. The page has a footer with a document identifier. A portion of a green binder or book cover is visible on the left side of the page.",
    "layout": "The page is arranged in a collage style with four distinct photo-and-caption blocks. A photo of Epstein and Ghislaine Maxwell is in the top right. A photo of Epstein and Adrianna Ross is in the middle left. A booking photo of Epstein is in the middle right. An aerial photo of 'The Stockade' is at the bottom. A document identifier is centered at the very bottom of the page.",
    "quality": "medium",
    "orientation": "portrait"
  },
  "text_extraction": {
    "full_text": "On the day the police investigation began, Epstein was photographed with Ghislaine Maxwell in New York City at the 2005 Wall Street concert series benefiting Wall Street Rising, at Cipriani in New York City, March 15, 2005. (Joe Shildhorn / Patrick McMullen)\n\nJeffrey Epstein, photographed with Adrianna Ross, attending the launch of Radar magazine held at the Hotel QT in New York City, May 2005 (Neil Rasmus / PatrickMcMullan.com / Sipa Press)\n\n2008 Palm Beach County Sheriff's Office booking photo of Jeffrey Epstein (Palm Beach County Sheriff's Office)\n\nThe Stockade, where Epstein served his sentence, photographed here in 2006, was located at 673 Fairgrounds Road in West Palm Beach, Florida. At the time, it was used as a minimum- and medium-security facility housing women and juveniles, as well as male inmates on a work-release program. (Smith Aerial Photos)\n\nHOUSE_OVERSIGHT_010489",
    "text_regions": [
      {
        "region": "caption",
        "text": "On the day the police investigation began, Epstein was photographed with Ghislaine Maxwell in New York City at the 2005 Wall Street concert series benefiting Wall Street Rising, at Cipriani in New York City, March 15, 2005. (Joe Shildhorn / Patrick McMullen)",
        "type": "printed"
      },
      {
        "region": "caption",
        "text": "Jeffrey Epstein, photographed with Adrianna Ross, attending the launch of Radar magazine held at the Hotel QT in New York City, May 2005 (Neil Rasmus / PatrickMcMullan.com / Sipa Press)",
        "type": "printed"
      },
      {
        "region": "caption",
        "text": "2008 Palm Beach County Sheriff's Office booking photo of Jeffrey Epstein (Palm Beach County Sheriff's Office)",
        "type": "printed"
      },
      {
        "region": "caption",
        "text": "The Stockade, where Epstein served his sentence, photographed here in 2006, was located at 673 Fairgrounds Road in West Palm Beach, Florida. At the time, it was used as a minimum- and medium-security facility housing women and juveniles, as well as male inmates on a work-release program. (Smith Aerial Photos)",
        "type": "printed"
      },
      {
        "region": "footer",
        "text": "HOUSE_OVERSIGHT_010489",
        "type": "printed"
      }
    ]
  },
  "structured_data": {
    "dates": [
      "2005-03-15",
      "2005-05",
      "2008",
      "2006"
    ],
    "people": [
      "Epstein",
      "Jeffrey Epstein",
      "Ghislaine Maxwell",
      "Joe Shildhorn",
      "Patrick McMullen",
      "Adrianna Ross",
      "Neil Rasmus"
    ],
    "organizations": [
      "Wall Street Rising",
      "PatrickMcMullan.com",
      "Sipa Press",
      "Palm Beach County Sheriff's Office",
      "Radar magazine",
      "Smith Aerial Photos",
      "House Oversight"
    ],
    "locations": [
      "New York City",
      "Cipriani in New York City",
      "Hotel QT in New York City",
      "The Stockade",
      "673 Fairgrounds Road in West Palm Beach, Florida",
      "West Palm Beach, Florida"
    ],
    "document_numbers": [
      "HOUSE_OVERSIGHT_010489"
    ],
    "financial_amounts": [],
    "contact_info": {
      "phone_numbers": [],
      "email_addresses": [],
      "addresses": [
        "673 Fairgrounds Road in West Palm Beach, Florida"
      ]
    },
    "signatures": [],
    "stamps_or_markings": []
  },
  "document_metadata": {
    "document_type": "photo_collage",
    "sender": null,
    "recipient": null,
    "subject": "Photographs related to Jeffrey Epstein, including associates, a booking photo, and a correctional facility.",
    "date": null,
    "references": [
      "HOUSE_OVERSIGHT_010489"
    ]
  },
  "confidence": {
    "text_extraction": 0.99,
    "structured_data": 0.98,
    "overall": 0.98
  },
  "notes": "The document appears to be an exhibit or part of a report, given the collection of captioned photos and the 'HOUSE_OVERSIGHT' identifier.",
  "file_path": "IMAGES\\001\\HOUSE_OVERSIGHT_010489.jpg",
  "house_oversight_id": "010489",
  "processing_metadata": {
    "processed_at": "2025-11-13T23:55:18.136610Z",
    "model": "gemini-2.5-pro"
  }
}