{
  "file_name": "HOUSE_OVERSIGHT_010614.jpg",
  "image_analysis": {
    "type": "document",
    "description": "A single-page document containing disclosures from Bank of America Merrill Lynch. The page is formatted with a main title, section headers, and multiple paragraphs of dense legal and financial text. A footer at the bottom includes a page number, document title, date, the company logo, and a document identifier.",
    "layout": "Standard portrait document layout with a title, two main sections with headers, body text in two columns, and a footer.",
    "quality": "high",
    "orientation": "portrait"
  },
  "text_extraction": {
    "full_text": "Disclosures\nImportant Disclosures\n\nBofA Merrill Lynch Research Personnel (including the analyst(s) responsible for this report) receive compensation based upon, among other factors, the overall profitability of Bank of America Corporation, including profits derived from investment banking. The analyst(s) responsible for this report may also receive compensation based upon, among other factors, the overall profitability of the Bank's sales and trading businesses relating to the class of securities or financial instruments for which such analyst is responsible.\nBofA Merrill Lynch Global Credit Research analysts regularly interact with sales and trading desk personnel in connection with their research, including to ascertain pricing and liquidity in the fixed income markets.\n\nOther Important Disclosures\n\nPrices are indicative and for information purposes only. Except as otherwise stated in the report, for the purpose of any recommendation in relation to: (i) an equity security, the price referenced is the publicly traded price of the security as of the close of business on the day prior to the date of the report or, if the report is published during intraday trading, the price referenced is indicative of the traded price as of the date and time of the report and are from various sources including Bank of America Merrill Lynch trading desks. The date and time of completion of the production of any recommendation in this report shall be the date and time of dissemination of this report as recorded in the report timestamp.\n\nThis report may refer to fixed income securities that may not be offered or sold in one or more states or jurisdictions. Readers of this report are advised that any discussion, recommendation or other mention of such securities is not a solicitation or offer to transact in such securities. Investors should contact their BofA Merrill Lynch representative or Merrill Lynch Financial Global Wealth Management financial advisor for information relating to fixed income securities\nRule 144A securities may be offered or sold only to persons in the U.S. who are Qualified Institutional Buyers within the meaning of Rule 144A under the Securities Act of 1933, as amended. SECURITIES DISCUSSED HEREIN MAY BE RATED BELOW INVESTMENT GRADE AND SHOULD THEREFORE ONLY BE CONSIDERED FOR INCLUSION IN ACCOUNTS QUALIFIED FOR SPECULATIVE INVESTMENT.\nRecipients who are not institutional investors or market professionals should seek the advice of their independent financial advisor before considering information in this report in connection with any investment decision, or for a necessary explanation of its contents.\nThe securities discussed in this report may be traded over-the-counter. Retail sales and/or distribution of this report may be made only in states where these securities are exempt from registration or have been qualified for sale.\nOfficers of MLPF&S or one or more of its affiliates (other than research analysts) may have a financial interest in securities of the issuer(s) or in related investments.\nThis report, and the securities discussed herein, may not be eligible for distribution or sale in all countries or to certain categories of investors.\nBofA Merrill Lynch Global Research policies relating to conflicts of interest are described at http://go.bofa.com/coi.\n\"BofA Merrill Lynch\" includes Merrill Lynch, Pierce, Fenner & Smith Incorporated (\"MLPF&S\") and its affiliates. Investors should contact their BofA Merrill Lynch representative or Merrill Lynch Global Wealth Management financial advisor if they have questions concerning this report. \"BofA Merrill Lynch\" and \"Merrill Lynch\" are each global brands for BofA Merrill Lynch Global Research.\nInformation relating to Non-US affiliates of BofA Merrill Lynch and Distribution of Affiliate Research Reports:\nMLPF&S distributes, or may in the future distribute, research reports of the following non-US affiliates in the US (short name: legal name, regulator): Merrill Lynch (South Africa): Merrill Lynch South Africa (Pty) Ltd., regulated by The Financial Service Board (South Africa) (PRA); Merrill Lynch International, regulated by the Financial Conduct Authority (FCA) and the Prudential Regulation Authority (PRA); Merrill Lynch (Australia): Merrill Lynch Equities (Australia) Limited, regulated by the Australian Securities and Investments Commission (ASIC); Merrill Lynch (Hong Kong): Merrill Lynch (Asia Pacific) Limited, regulated by the Hong Kong Securities and Futures Commission (HKSFC); Merrill Lynch (Singapore): Merrill Lynch (Singapore) Pte Ltd, regulated by the Monetary Authority of Singapore (MAS); Merrill Lynch (Canada): Merrill Lynch Canada Inc, regulated by the Investment Industry Regulatory Organization of Canada; Merrill Lynch (Mexico): Merrill Lynch Mexico, SA de CV, Casa de Bolsa, regulated by the Comisión Nacional Bancaria y de Valores; Merrill Lynch (Argentina): Merrill Lynch Argentina SA, regulated by Comisión Nacional de Valores; Merrill Lynch (Japan): Merrill Lynch Japan Securities Co., Ltd., regulated by the Financial Services Agency; Merrill Lynch (Seoul): Merrill Lynch International Incorporated (Seoul Branch) regulated by the Financial Supervisory Service; Merrill Lynch (Taiwan): Merrill Lynch Securities (Taiwan) Ltd., regulated by the Securities and Futures Bureau; DSP Merrill Lynch (India): DSP Merrill Lynch Limited, regulated by the Securities and Exchange Board of India; PT Merrill Lynch Indonesia, regulated by Otoritas Jasa Keuangan (OJK); Merrill Lynch (Israel): Merrill Lynch Israel Limited, regulated by Israel Securities Authority; Merrill Lynch (Russia): OOO Merrill Lynch Securities, Moscow, regulated by the Central Bank of the Russian Federation; Merrill Lynch (DIFC): Merrill Lynch International (DIFC Branch), regulated by the Dubai Financial Services Authority (DFSA); Merrill Lynch (Spain): Merrill Lynch Capital Markets Espana, S.A.S.V., regulated by Comisión Nacional del Mercado De Valores; Merrill Lynch (Brazil): Bank of America Merrill Lynch Banco Multiplo S.A., regulated by Comissão de Valores Mobiliários; Merrill Lynch Kingdom of Saudi Arabia Company, regulated by the Capital Market Authority.\nThis research report: has been approved for publication and is distributed in the United Kingdom (UK) to professional clients and eligible counterparties (as each is defined in the rules of the FCA and the PRA) by MLI (UK) and Bank of America Merrill Lynch International Bank Limited, London Branch, which is authorized by the PRA and regulated by the FCA and the PRA - details about the extent of our regulation by the FCA and PRA are available from us on request; has been considered and distributed in Japan by Merrill Lynch (Japan), a registered securities dealer under the Financial Instruments and Exchange Act in Japan; is issued and distributed in Hong Kong by Merrill Lynch (Hong Kong) which is regulated by HKSFC (research reports containing any information in relation to, or advice on, futures contracts are not intended for issuance or distribution to, or use by, any person in Hong Kong); is issued and distributed in Taiwan by Merrill Lynch (Taiwan); is issued and distributed in India by DSP Merrill Lynch (India); and is issued and distributed in Singapore to institutional investors and/or accredited investors (each as defined under the Financial Advisers Regulations) by Merrill Lynch International Bank Limited (Merchant Bank) (MLIBLMB) and Merrill Lynch (Singapore) (Company Registration Nos F 06872E and 198602883D respectively). MLIBLMB and Merrill Lynch (Singapore) are regulated by MAS. Bank of America N.A., Australian Branch (ABN 65 006 276 795), AFS License 235132 (BANA Australia) and Merrill Lynch Equities (Australia) Limited (ABN 65 006 276 795), AFS License 235132 (MLEA) distribute this report in Australia only to 'Wholesale' clients as defined by s.761G of the Corporations Act 2001. With the exception of BANA Australia, neither MLEA nor any of its affiliates involved in preparing this research report is an Authorised Deposit-Taking Institution under the Banking Act 1959 nor regulated by the Australian Prudential Regulation Authority. No approval is required for publication or distribution of this report in Brazil and its local distribution is by Merrill Lynch (Brazil) in accordance with applicable regulations. Merrill Lynch (DIFC) reports prepared and issued by Merrill Lynch (DIFC) are done so in accordance with the requirements of the DFSA conduct of business rules. Bank of America Merrill Lynch International Limited, Frankfurt Branch (BAMLI Frankfurt) distributes this report in Germany and is regulated by BaFin.\nThis research report has been prepared and issued by MLPF&S or one or more of its non-US affiliates. MLPF&S is the distributor of this research report in the US and accepts full responsibility for research reports of its non-US affiliates distributed to MLPF&S clients in the US. Any US person receiving this research report and wishing to effect any transaction in any security discussed in the report should do so through MLPF&S and not such foreign affiliates. Hong Kong recipients of this research report should contact Merrill Lynch (Asia Pacific) Limited in respect of any matters relating to dealing in securities (and not futures contracts) or provision of specific advice on securities (and not futures contracts). Singapore recipients of this research report should contact Merrill Lynch International Bank Limited (Merchant Bank) and/or Merrill Lynch (Singapore) Pte Ltd in respect of any matters arising from, or in connection with, this research report.\nGeneral Investment Related Disclosures:\nTaiwan Readers: Neither the information nor any opinion expressed herein constitutes an offer or a solicitation of an offer to transact in any securities or other financial instrument. No part of this report may be used or reproduced or quoted in any manner whatsoever in Taiwan by the press or any other person without the express written consent of BofA Merrill Lynch.\n\n6 Liquid Insight | 22 September 2016\n\nBank of America\nMerrill Lynch\n\nHOUSE_OVERSIGHT_010614",
    "text_regions": [
      {
        "region": "header",
        "text": "Disclosures\nImportant Disclosures",
        "type": "printed"
      },
      {
        "region": "body",
        "text": "BofA Merrill Lynch Research Personnel (including the analyst(s) responsible for this report) receive compensation based upon, among other factors, the overall profitability of Bank of America Corporation, including profits derived from investment banking. The analyst(s) responsible for this report may also receive compensation based upon, among other factors, the overall profitability of the Bank's sales and trading businesses relating to the class of securities or financial instruments for which such analyst is responsible.\nBofA Merrill Lynch Global Credit Research analysts regularly interact with sales and trading desk personnel in connection with their research, including to ascertain pricing and liquidity in the fixed income markets.\n\nOther Important Disclosures\n\nPrices are indicative and for information purposes only. Except as otherwise stated in the report, for the purpose of any recommendation in relation to: (i) an equity security, the price referenced is the publicly traded price of the security as of the close of business on the day prior to the date of the report or, if the report is published during intraday trading, the price referenced is indicative of the traded price as of the date and time of the report and are from various sources including Bank of America Merrill Lynch trading desks. The date and time of completion of the production of any recommendation in this report shall be the date and time of dissemination of this report as recorded in the report timestamp.\n\nThis report may refer to fixed income securities that may not be offered or sold in one or more states or jurisdictions. Readers of this report are advised that any discussion, recommendation or other mention of such securities is not a solicitation or offer to transact in such securities. Investors should contact their BofA Merrill Lynch representative or Merrill Lynch Financial Global Wealth Management financial advisor for information relating to fixed income securities\nRule 144A securities may be offered or sold only to persons in the U.S. who are Qualified Institutional Buyers within the meaning of Rule 144A under the Securities Act of 1933, as amended. SECURITIES DISCUSSED HEREIN MAY BE RATED BELOW INVESTMENT GRADE AND SHOULD THEREFORE ONLY BE CONSIDERED FOR INCLUSION IN ACCOUNTS QUALIFIED FOR SPECULATIVE INVESTMENT.\nRecipients who are not institutional investors or market professionals should seek the advice of their independent financial advisor before considering information in this report in connection with any investment decision, or for a necessary explanation of its contents.\nThe securities discussed in this report may be traded over-the-counter. Retail sales and/or distribution of this report may be made only in states where these securities are exempt from registration or have been qualified for sale.\nOfficers of MLPF&S or one or more of its affiliates (other than research analysts) may have a financial interest in securities of the issuer(s) or in related investments.\nThis report, and the securities discussed herein, may not be eligible for distribution or sale in all countries or to certain categories of investors.\nBofA Merrill Lynch Global Research policies relating to conflicts of interest are described at http://go.bofa.com/coi.\n\"BofA Merrill Lynch\" includes Merrill Lynch, Pierce, Fenner & Smith Incorporated (\"MLPF&S\") and its affiliates. Investors should contact their BofA Merrill Lynch representative or Merrill Lynch Global Wealth Management financial advisor if they have questions concerning this report. \"BofA Merrill Lynch\" and \"Merrill Lynch\" are each global brands for BofA Merrill Lynch Global Research.\nInformation relating to Non-US affiliates of BofA Merrill Lynch and Distribution of Affiliate Research Reports:\nMLPF&S distributes, or may in the future distribute, research reports of the following non-US affiliates in the US (short name: legal name, regulator): Merrill Lynch (South Africa): Merrill Lynch South Africa (Pty) Ltd., regulated by The Financial Service Board (South Africa) (PRA); Merrill Lynch International, regulated by the Financial Conduct Authority (FCA) and the Prudential Regulation Authority (PRA); Merrill Lynch (Australia): Merrill Lynch Equities (Australia) Limited, regulated by the Australian Securities and Investments Commission (ASIC); Merrill Lynch (Hong Kong): Merrill Lynch (Asia Pacific) Limited, regulated by the Hong Kong Securities and Futures Commission (HKSFC); Merrill Lynch (Singapore): Merrill Lynch (Singapore) Pte Ltd, regulated by the Monetary Authority of Singapore (MAS); Merrill Lynch (Canada): Merrill Lynch Canada Inc, regulated by the Investment Industry Regulatory Organization of Canada; Merrill Lynch (Mexico): Merrill Lynch Mexico, SA de CV, Casa de Bolsa, regulated by the Comisión Nacional Bancaria y de Valores; Merrill Lynch (Argentina): Merrill Lynch Argentina SA, regulated by Comisión Nacional de Valores; Merrill Lynch (Japan): Merrill Lynch Japan Securities Co., Ltd., regulated by the Financial Services Agency; Merrill Lynch (Seoul): Merrill Lynch International Incorporated (Seoul Branch) regulated by the Financial Supervisory Service; Merrill Lynch (Taiwan): Merrill Lynch Securities (Taiwan) Ltd., regulated by the Securities and Futures Bureau; DSP Merrill Lynch (India): DSP Merrill Lynch Limited, regulated by the Securities and Exchange Board of India; PT Merrill Lynch Indonesia, regulated by Otoritas Jasa Keuangan (OJK); Merrill Lynch (Israel): Merrill Lynch Israel Limited, regulated by Israel Securities Authority; Merrill Lynch (Russia): OOO Merrill Lynch Securities, Moscow, regulated by the Central Bank of the Russian Federation; Merrill Lynch (DIFC): Merrill Lynch International (DIFC Branch), regulated by the Dubai Financial Services Authority (DFSA); Merrill Lynch (Spain): Merrill Lynch Capital Markets Espana, S.A.S.V., regulated by Comisión Nacional del Mercado De Valores; Merrill Lynch (Brazil): Bank of America Merrill Lynch Banco Multiplo S.A., regulated by Comissão de Valores Mobiliários; Merrill Lynch Kingdom of Saudi Arabia Company, regulated by the Capital Market Authority.\nThis research report: has been approved for publication and is distributed in the United Kingdom (UK) to professional clients and eligible counterparties (as each is defined in the rules of the FCA and the PRA) by MLI (UK) and Bank of America Merrill Lynch International Bank Limited, London Branch, which is authorized by the PRA and regulated by the FCA and the PRA - details about the extent of our regulation by the FCA and PRA are available from us on request; has been considered and distributed in Japan by Merrill Lynch (Japan), a registered securities dealer under the Financial Instruments and Exchange Act in Japan; is issued and distributed in Hong Kong by Merrill Lynch (Hong Kong) which is regulated by HKSFC (research reports containing any information in relation to, or advice on, futures contracts are not intended for issuance or distribution to, or use by, any person in Hong Kong); is issued and distributed in Taiwan by Merrill Lynch (Taiwan); is issued and distributed in India by DSP Merrill Lynch (India); and is issued and distributed in Singapore to institutional investors and/or accredited investors (each as defined under the Financial Advisers Regulations) by Merrill Lynch International Bank Limited (Merchant Bank) (MLIBLMB) and Merrill Lynch (Singapore) (Company Registration Nos F 06872E and 198602883D respectively). MLIBLMB and Merrill Lynch (Singapore) are regulated by MAS. Bank of America N.A., Australian Branch (ABN 65 006 276 795), AFS License 235132 (BANA Australia) and Merrill Lynch Equities (Australia) Limited (ABN 65 006 276 795), AFS License 235132 (MLEA) distribute this report in Australia only to 'Wholesale' clients as defined by s.761G of the Corporations Act 2001. With the exception of BANA Australia, neither MLEA nor any of its affiliates involved in preparing this research report is an Authorised Deposit-Taking Institution under the Banking Act 1959 nor regulated by the Australian Prudential Regulation Authority. No approval is required for publication or distribution of this report in Brazil and its local distribution is by Merrill Lynch (Brazil) in accordance with applicable regulations. Merrill Lynch (DIFC) reports prepared and issued by Merrill Lynch (DIFC) are done so in accordance with the requirements of the DFSA conduct of business rules. Bank of America Merrill Lynch International Limited, Frankfurt Branch (BAMLI Frankfurt) distributes this report in Germany and is regulated by BaFin.\nThis research report has been prepared and issued by MLPF&S or one or more of its non-US affiliates. MLPF&S is the distributor of this research report in the US and accepts full responsibility for research reports of its non-US affiliates distributed to MLPF&S clients in the US. Any US person receiving this research report and wishing to effect any transaction in any security discussed in the report should do so through MLPF&S and not such foreign affiliates. Hong Kong recipients of this research report should contact Merrill Lynch (Asia Pacific) Limited in respect of any matters relating to dealing in securities (and not futures contracts) or provision of specific advice on securities (and not futures contracts). Singapore recipients of this research report should contact Merrill Lynch International Bank Limited (Merchant Bank) and/or Merrill Lynch (Singapore) Pte Ltd in respect of any matters arising from, or in connection with, this research report.\nGeneral Investment Related Disclosures:\nTaiwan Readers: Neither the information nor any opinion expressed herein constitutes an offer or a solicitation of an offer to transact in any securities or other financial instrument. No part of this report may be used or reproduced or quoted in any manner whatsoever in Taiwan by the press or any other person without the express written consent of BofA Merrill Lynch.",
        "type": "printed"
      },
      {
        "region": "footer",
        "text": "6 Liquid Insight | 22 September 2016\n\nBank of America\nMerrill Lynch\n\nHOUSE_OVERSIGHT_010614",
        "type": "printed"
      }
    ]
  },
  "structured_data": {
    "dates": [
      "2016-09-22",
      "1933",
      "2001",
      "1959"
    ],
    "people": [],
    "organizations": [
      "BofA Merrill Lynch",
      "Bank of America Corporation",
      "BofA Merrill Lynch Global Credit Research",
      "Merrill Lynch, Pierce, Fenner & Smith Incorporated",
      "MLPF&S",
      "Merrill Lynch Financial Global Wealth Management",
      "BofA Merrill Lynch Global Research",
      "Merrill Lynch",
      "Merrill Lynch (South Africa)",
      "Merrill Lynch South Africa (Pty) Ltd.",
      "The Financial Service Board (South Africa)",
      "Merrill Lynch International",
      "Financial Conduct Authority",
      "FCA",
      "Prudential Regulation Authority",
      "PRA",
      "Merrill Lynch (Australia)",
      "Merrill Lynch Equities (Australia) Limited",
      "Australian Securities and Investments Commission",
      "ASIC",
      "Merrill Lynch (Hong Kong)",
      "Merrill Lynch (Asia Pacific) Limited",
      "Hong Kong Securities and Futures Commission",
      "HKSFC",
      "Merrill Lynch (Singapore)",
      "Merrill Lynch (Singapore) Pte Ltd",
      "Monetary Authority of Singapore",
      "MAS",
      "Merrill Lynch (Canada)",
      "Merrill Lynch Canada Inc",
      "Investment Industry Regulatory Organization of Canada",
      "Merrill Lynch (Mexico)",
      "Merrill Lynch Mexico, SA de CV, Casa de Bolsa",
      "Comisión Nacional Bancaria y de Valores",
      "Merrill Lynch (Argentina)",
      "Merrill Lynch Argentina SA",
      "Comisión Nacional de Valores",
      "Merrill Lynch (Japan)",
      "Merrill Lynch Japan Securities Co., Ltd.",
      "Financial Services Agency",
      "Merrill Lynch (Seoul)",
      "Merrill Lynch International Incorporated (Seoul Branch)",
      "Financial Supervisory Service",
      "Merrill Lynch (Taiwan)",
      "Merrill Lynch Securities (Taiwan) Ltd.",
      "Securities and Futures Bureau",
      "DSP Merrill Lynch (India)",
      "DSP Merrill Lynch Limited",
      "Securities and Exchange Board of India",
      "PT Merrill Lynch Indonesia",
      "Otoritas Jasa Keuangan",
      "OJK",
      "Merrill Lynch (Israel)",
      "Merrill Lynch Israel Limited",
      "Israel Securities Authority",
      "Merrill Lynch (Russia)",
      "OOO Merrill Lynch Securities, Moscow",
      "Central Bank of the Russian Federation",
      "Merrill Lynch (DIFC)",
      "Merrill Lynch International (DIFC Branch)",
      "Dubai Financial Services Authority",
      "DFSA",
      "Merrill Lynch (Spain)",
      "Merrill Lynch Capital Markets Espana, S.A.S.V.",
      "Comisión Nacional del Mercado De Valores",
      "Merrill Lynch (Brazil)",
      "Bank of America Merrill Lynch Banco Multiplo S.A.",
      "Comissão de Valores Mobiliários",
      "Merrill Lynch Kingdom of Saudi Arabia Company",
      "Capital Market Authority",
      "MLI (UK)",
      "Bank of America Merrill Lynch International Bank Limited, London Branch",
      "Merrill Lynch International Bank Limited (Merchant Bank)",
      "MLIBLMB",
      "Bank of America N.A., Australian Branch",
      "BANA Australia",
      "MLEA",
      "Australian Prudential Regulation Authority",
      "Bank of America Merrill Lynch International Limited, Frankfurt Branch",
      "BAMLI Frankfurt",
      "BaFin"
    ],
    "locations": [
      "U.S.",
      "South Africa",
      "Australia",
      "Hong Kong",
      "Singapore",
      "Canada",
      "Mexico",
      "Argentina",
      "Japan",
      "Seoul",
      "Taiwan",
      "India",
      "Indonesia",
      "Israel",
      "Russia",
      "Moscow",
      "DIFC",
      "Spain",
      "Brazil",
      "Kingdom of Saudi Arabia",
      "United Kingdom",
      "UK",
      "London",
      "Germany",
      "Frankfurt"
    ],
    "document_numbers": [
      "HOUSE_OVERSIGHT_010614",
      "Rule 144A",
      "F 06872E",
      "198602883D",
      "ABN 65 006 276 795",
      "AFS License 235132",
      "s.761G"
    ],
    "financial_amounts": [],
    "contact_info": {
      "phone_numbers": [],
      "email_addresses": [],
      "addresses": [],
      "urls": [
        "http://go.bofa.com/coi"
      ]
    },
    "signatures": [],
    "stamps_or_markings": [
      "HOUSE_OVERSIGHT_010614"
    ]
  },
  "document_metadata": {
    "document_type": "disclosures",
    "sender": "Bank of America Merrill Lynch",
    "recipient": null,
    "subject": "Important Disclosures and Other Important Disclosures related to financial research reports.",
    "date": "2016-09-22",
    "references": [
      "Liquid Insight"
    ]
  },
  "confidence": {
    "text_extraction": 0.99,
    "structured_data": 0.98,
    "overall": 0.98
  },
  "notes": "The document is a standard legal/financial disclosure page, likely an appendix to a research report titled 'Liquid Insight'. The document identifier 'HOUSE_OVERSIGHT_010614' suggests it is part of a collection of documents for the House Oversight Committee.",
  "file_path": "IMAGES\\001\\HOUSE_OVERSIGHT_010614.jpg",
  "house_oversight_id": "010614",
  "processing_metadata": {
    "processed_at": "2025-11-14T00:45:52.787254Z",
    "model": "gemini-2.5-pro"
  }
}