{
  "file_name": "HOUSE_OVERSIGHT_010488.jpg",
  "image_analysis": {
    "type": "document",
    "description": "A scanned page from a document, featuring a collage of seven photographs with corresponding captions. The photographs depict various individuals, including Jeffrey Epstein, Virginia Roberts, Ghislaine Maxwell, Prince Andrew, and Alan Dershowitz, in different settings. The page has a white background with printed text and images. A document control number is visible at the bottom right corner.",
    "layout": "The page is arranged in a multi-column, collage-style layout. Photographs are placed on both the left and right sides of the page, with text captions adjacent to each image. A footer with a document number is at the very bottom.",
    "quality": "medium",
    "orientation": "portrait"
  },
  "text_extraction": {
    "full_text": "exner, photographed\nne in New York City,\nLynn Goldsmith)\n\nVirginia Roberts, age\nfifteen; photo reportedly\ntaken by Jeffrey Epstein in\nNew York City (Virginia\nRoberts Affidavit, US\nDistrict Southern Court of\nFlorida)\n\n(L to R) Deborah\nBlohm, Jeffrey Epstein,\nGhislaine Maxwell, and\nGwendolyn Beck attend a\nreception at Mar-a-Lago,\n1995. (Davidoff Studios)\n\n(L to R) Prince Andrew, Virginia Roberts,\nand Ghislaine Maxwell; photo reportedly\ntaken by Epstein with Roberts's camera\nin Maxwell's London town house.\nRoberts was seventeen years old at this\ntime. (Virginia Roberts Affidavit, US\nDistrict Southern Court of Florida)\n\nVirginia Roberts, age seventeen;\nphoto reportedly taken by\nJeffrey Epstein at Zorro Ranch,\nhis New Mexico property,\nin winter (Virginia Roberts\nAffidavit, US District Southern\nCourt of Florida)\n\nHARVARD\n\nJeffrey Epstein with Professor\nAlan Dershowitz in Cambridge,\nMA, September 8, 2004 (© Rick\nFriedman / Corbis)\n\nHOUSE_OVERSIGHT_010488",
    "text_regions": [
      {
        "region": "caption",
        "text": "exner, photographed\nne in New York City,\nLynn Goldsmith)",
        "type": "printed"
      },
      {
        "region": "caption",
        "text": "Virginia Roberts, age\nfifteen; photo reportedly\ntaken by Jeffrey Epstein in\nNew York City (Virginia\nRoberts Affidavit, US\nDistrict Southern Court of\nFlorida)",
        "type": "printed"
      },
      {
        "region": "caption",
        "text": "(L to R) Deborah\nBlohm, Jeffrey Epstein,\nGhislaine Maxwell, and\nGwendolyn Beck attend a\nreception at Mar-a-Lago,\n1995. (Davidoff Studios)",
        "type": "printed"
      },
      {
        "region": "caption",
        "text": "(L to R) Prince Andrew, Virginia Roberts,\nand Ghislaine Maxwell; photo reportedly\ntaken by Epstein with Roberts's camera\nin Maxwell's London town house.\nRoberts was seventeen years old at this\ntime. (Virginia Roberts Affidavit, US\nDistrict Southern Court of Florida)",
        "type": "printed"
      },
      {
        "region": "caption",
        "text": "Virginia Roberts, age seventeen;\nphoto reportedly taken by\nJeffrey Epstein at Zorro Ranch,\nhis New Mexico property,\nin winter (Virginia Roberts\nAffidavit, US District Southern\nCourt of Florida)",
        "type": "printed"
      },
      {
        "region": "caption",
        "text": "Jeffrey Epstein with Professor\nAlan Dershowitz in Cambridge,\nMA, September 8, 2004 (© Rick\nFriedman / Corbis)",
        "type": "printed"
      },
      {
        "region": "clothing_text",
        "text": "HARVARD",
        "type": "printed"
      },
      {
        "region": "footer",
        "text": "HOUSE_OVERSIGHT_010488",
        "type": "printed"
      }
    ]
  },
  "structured_data": {
    "dates": [
      "1995",
      "2004-09-08"
    ],
    "people": [
      "exner",
      "Lynn Goldsmith",
      "Virginia Roberts",
      "Jeffrey Epstein",
      "Deborah Blohm",
      "Ghislaine Maxwell",
      "Gwendolyn Beck",
      "Prince Andrew",
      "Alan Dershowitz",
      "Rick Friedman"
    ],
    "organizations": [
      "US District Southern Court of Florida",
      "Davidoff Studios",
      "Corbis",
      "HARVARD"
    ],
    "locations": [
      "New York City",
      "Florida",
      "Mar-a-Lago",
      "London",
      "Zorro Ranch",
      "New Mexico",
      "Cambridge, MA"
    ],
    "document_numbers": [
      "HOUSE_OVERSIGHT_010488"
    ],
    "financial_amounts": [],
    "contact_info": {
      "phone_numbers": [],
      "email_addresses": [],
      "addresses": []
    },
    "signatures": [],
    "stamps_or_markings": [
      "Document number: HOUSE_OVERSIGHT_010488"
    ]
  },
  "document_metadata": {
    "document_type": "photo_collage",
    "sender": null,
    "recipient": null,
    "subject": "Photographs related to Jeffrey Epstein and associates",
    "date": null,
    "references": [
      "Virginia Roberts Affidavit"
    ]
  },
  "confidence": {
    "text_extraction": 0.98,
    "structured_data": 0.99,
    "overall": 0.98
  },
  "notes": "The document is a single page from a larger collection, identified by the Bates number 'HOUSE_OVERSIGHT_010488'. The text consists entirely of captions for the accompanying photographs. The name 'exner' is partially cut off at the top of the page.",
  "file_path": "IMAGES\\001\\HOUSE_OVERSIGHT_010488.jpg",
  "house_oversight_id": "010488",
  "processing_metadata": {
    "processed_at": "2025-11-13T20:45:16.126813Z",
    "model": "gemini-2.5-pro"
  }
}